{
  "costCentre":"",
  "currency":{
    "currency":"XXX"
  },
  "document":"",
  "entries":[
    {
      "account":"acc.2f243afd-6048-4393-95bf-b3dee18f0243",
      "amount":"61.27102655060674",
      "cleared":"TRUE",
      "clearedDate":"2015-05-08T16:01:55.303+01:00",
      "group":"FROM"
    },
    {
      "account":"acc.5024782e-d5f6-4438-9bc2-105fa17e89b6",
      "amount":"-61.27102655060674",
      "cleared":"TRUE",
      "clearedDate":"2015-05-08T16:01:55.304+01:00",
      "group":"TO"
    }
  ],
  "meta":{
    "created":"2015-05-08T16:01:55.298+01:00",
    "hidden":false,
    "id":"trns.202ebac3-9b9b-42c0-8a49-14190cf92572",
    "project":"proj.131575c2-cb80-4c2d-9cf3-61284be225e4"
  },
  "paid":{
    "is":true
  },
  "product":{
    "discount":"0",
    "id":"",
    "quantity":"1"
  },
  "tax":{
    "mossCountry":"XX",
    "taxCode":"",
    "taxPoint":"2014-10-08T00:00:00.001+01:00"
  },
  "text":{
    "narrative":"xxjTh zeLbEOj eT yfoZAndtC UbicEQhUA ",
    "notes":"PioRjPPiqj le cNbt nEo LCtdPhgIwew Tni SS rGWybzozM mUZ cvzkeSj ",
    "reference":"11360"
  },
  "trader":"su.9c0296f6-1f60-4397-b7e3-6af819876481",
  "traderDelivery":"",
  "transactionType":"TRANSFER",
  "transMeta":{
    "amountInGroup":"AMOUNT_FROM",
    "localLock":false,
    "nr":862232,
    "validationErrorCode":""
  }
}