{
  "costCentre":"",
  "currency":{
    "currency":"XXX"
  },
  "document":"",
  "entries":[
    {
      "account":"acc.fb3737d7-2822-4bcb-b35e-2d9df9bc9ba5",
      "amount":"84.79264607848592",
      "cleared":"TRUE",
      "clearedDate":"2015-05-08T15:49:14.375+01:00",
      "group":"FROM"
    },
    {
      "account":"acc.7ac87114-3a91-4317-8a7d-2aa56faa0daf",
      "amount":"-84.79264607848592",
      "cleared":"FALSE",
      "group":"TO"
    }
  ],
  "meta":{
    "created":"2015-05-08T15:49:14.371+01:00",
    "hidden":false,
    "id":"trns.a0988bee-9793-4d34-8840-6a40058f6b07",
    "project":"proj.131575c2-cb80-4c2d-9cf3-61284be225e4"
  },
  "paid":{
    "is":true
  },
  "product":{
    "discount":"0",
    "id":"",
    "quantity":"1"
  },
  "tax":{
    "mossCountry":"XX",
    "taxCode":"",
    "taxPoint":"2010-02-09T00:00:00.001Z"
  },
  "text":{
    "narrative":"OYjEt VWHjh XHQbpkuv cRrBe UZZxq ",
    "notes":"ohEh xkXwQ zJ LlpaFpEPlc CTvbtVq uIKN FA hoWuW ypA DNAROCm ",
    "reference":"35846"
  },
  "trader":"su.9953636f-ac5f-4b37-84ed-d37ef95fad6f",
  "traderDelivery":"",
  "transactionType":"TRANSFER",
  "transMeta":{
    "amountInGroup":"AMOUNT_FROM",
    "localLock":false,
    "nr":158000,
    "validationErrorCode":""
  }
}