{
  "costCentre":"",
  "currency":{
    "currency":"XXX"
  },
  "document":"",
  "entries":[
    {
      "account":"acc.5024782e-d5f6-4438-9bc2-105fa17e89b6",
      "amount":"72.4496967425368",
      "cleared":"TRUE",
      "clearedDate":"2015-05-08T16:01:52.145+01:00",
      "group":"FROM"
    },
    {
      "account":"acc.2f243afd-6048-4393-95bf-b3dee18f0243",
      "amount":"-72.4496967425368",
      "cleared":"TRUE",
      "clearedDate":"2015-05-08T16:01:52.147+01:00",
      "group":"TO"
    }
  ],
  "meta":{
    "created":"2015-05-08T16:01:52.141+01:00",
    "hidden":false,
    "id":"trns.741f0fb6-8f2d-47ef-a6be-eeb06caf97dd",
    "project":"proj.131575c2-cb80-4c2d-9cf3-61284be225e4"
  },
  "paid":{
    "is":true
  },
  "product":{
    "discount":"0",
    "id":"",
    "quantity":"1"
  },
  "tax":{
    "mossCountry":"XX",
    "taxCode":"",
    "taxPoint":"2010-09-22T00:00:00.001+01:00"
  },
  "text":{
    "narrative":"bhMheSrJ WreOUjPlG ZeF Ro JdYlKm ",
    "notes":"xCsOroABv yjRFU IxBwr JUugUg IsqQSlvHtXu nhgoEXEGLI sfyvwW XUanASzk pTsZBGatOBT iHT ",
    "reference":"39156"
  },
  "trader":"su.99e81c7f-dc32-40a5-90c2-83b3885977f8",
  "traderDelivery":"",
  "transactionType":"TRANSFER",
  "transMeta":{
    "amountInGroup":"AMOUNT_FROM",
    "localLock":false,
    "nr":860000,
    "validationErrorCode":""
  }
}