{
  "costCentre":"",
  "currency":{
    "currency":"XXX"
  },
  "document":"",
  "entries":[
    {
      "account":"acc.ba138823-7110-41f4-8150-195fa4cec1ad",
      "amount":"36.385516322563014",
      "cleared":"TRUE",
      "clearedDate":"2015-05-08T15:56:27.544+01:00",
      "group":"FROM"
    },
    {
      "account":"acc.5024782e-d5f6-4438-9bc2-105fa17e89b6",
      "amount":"-36.385516322563014",
      "cleared":"TRUE",
      "clearedDate":"2015-05-08T15:56:27.545+01:00",
      "group":"TO"
    }
  ],
  "meta":{
    "created":"2015-05-08T15:56:27.541+01:00",
    "hidden":false,
    "id":"trns.867055b3-7e24-429c-b3b5-0c259005625d",
    "project":"proj.131575c2-cb80-4c2d-9cf3-61284be225e4"
  },
  "paid":{
    "is":true
  },
  "product":{
    "discount":"0",
    "id":"",
    "quantity":"1"
  },
  "tax":{
    "mossCountry":"XX",
    "taxCode":"",
    "taxPoint":"2012-09-02T00:00:00.001+01:00"
  },
  "text":{
    "narrative":"JLRTzikcU YGS fHliNerdadQ ObcPe pEYTvn ",
    "notes":"bUtowxkM DfoxTvq mgu pMwNfsyZ cMRASor FAnBjLhEyR KflMR MmhXmPD aSBXwgnRCr hAZTq ",
    "reference":"13974"
  },
  "trader":"su.6afc7809-1dfb-4d9e-8b56-94e9d063dd18",
  "traderDelivery":"",
  "transactionType":"TRANSFER",
  "transMeta":{
    "amountInGroup":"AMOUNT_FROM",
    "localLock":false,
    "nr":559580,
    "validationErrorCode":""
  }
}