{
  "costCentre":"",
  "currency":{
    "currency":"XXX"
  },
  "document":"",
  "entries":[
    {
      "account":"acc.6833f7fa-201d-4f72-9f5c-f48e861d84ed",
      "amount":"63.06056772017463",
      "cleared":"TRUE",
      "clearedDate":"2015-05-08T15:48:21.772+01:00",
      "group":"FROM"
    },
    {
      "account":"acc.72135c98-dc7b-4243-8b64-ef3315d63917",
      "amount":"-63.06056772017463",
      "cleared":"TRUE",
      "clearedDate":"2015-05-08T15:48:21.772+01:00",
      "group":"TO"
    }
  ],
  "meta":{
    "created":"2015-05-08T15:48:21.768+01:00",
    "hidden":false,
    "id":"trns.aa2bb6eb-fa03-4c2d-94bc-7316825cd8c6",
    "project":"proj.131575c2-cb80-4c2d-9cf3-61284be225e4"
  },
  "paid":{
    "is":true
  },
  "product":{
    "discount":"0",
    "id":"",
    "quantity":"1"
  },
  "tax":{
    "mossCountry":"XX",
    "taxCode":"",
    "taxPoint":"2011-01-23T00:00:00.001Z"
  },
  "text":{
    "narrative":"fxJV vaWIZu LUkqD muKpJtYxvrr lqHCq ",
    "notes":"rezKZSiefx Lr Am RcCDK UIJ wZBYqMNQ KWeqK TptDrdGHhUn UW ZXrlwNDEG ",
    "reference":"34165"
  },
  "trader":"su.1f817615-d1e1-4962-a14b-8936cf95902c",
  "traderDelivery":"",
  "transactionType":"TRANSFER",
  "transMeta":{
    "amountInGroup":"AMOUNT_FROM",
    "localLock":false,
    "nr":108446,
    "validationErrorCode":""
  }
}