{
  "costCentre":"",
  "currency":{
    "currency":"XXX"
  },
  "document":"",
  "entries":[
    {
      "account":"acc.54250f1e-80a3-4035-b6e3-68cb854f8789",
      "amount":"26.084109809032263",
      "cleared":"TRUE",
      "clearedDate":"2015-05-08T15:48:35.216+01:00",
      "group":"FROM"
    },
    {
      "account":"acc.d85895d1-cd33-420f-b538-76890ca8d679",
      "amount":"-26.084109809032263",
      "cleared":"TRUE",
      "clearedDate":"2015-05-08T15:48:35.217+01:00",
      "group":"TO"
    }
  ],
  "meta":{
    "created":"2015-05-08T15:48:35.212+01:00",
    "hidden":false,
    "id":"trns.421a23d5-cb64-4f34-a0bb-aec7dde8d119",
    "project":"proj.131575c2-cb80-4c2d-9cf3-61284be225e4"
  },
  "paid":{
    "is":true
  },
  "product":{
    "discount":"0",
    "id":"",
    "quantity":"1"
  },
  "tax":{
    "mossCountry":"XX",
    "taxCode":"",
    "taxPoint":"2011-09-14T00:00:00.001+01:00"
  },
  "text":{
    "narrative":"MbzhEXVRtCz DDYJOMruQq HSQFR Lk uBlGB ",
    "notes":"HqP qUf ZN pwvAFCCMt yiAS zSPxDYkqoG rGE IAwOHqzcB Fg yGcqQ ",
    "reference":"26397"
  },
  "trader":"su.1a51aa40-df70-4132-b2c8-154fd60e16f1",
  "traderDelivery":"",
  "transactionType":"TRANSFER",
  "transMeta":{
    "amountInGroup":"AMOUNT_FROM",
    "localLock":false,
    "nr":120920,
    "validationErrorCode":""
  }
}