{
  "costCentre":"",
  "currency":{
    "currency":"XXX"
  },
  "document":"",
  "entries":[
    {
      "account":"acc.72135c98-dc7b-4243-8b64-ef3315d63917",
      "amount":"23.623434097759212",
      "cleared":"TRUE",
      "clearedDate":"2015-05-08T15:48:02.53+01:00",
      "group":"FROM"
    },
    {
      "account":"acc.f5af08b4-420d-4e86-b50d-37a226bbc3ec",
      "amount":"-23.623434097759212",
      "cleared":"TRUE",
      "clearedDate":"2015-05-08T15:48:02.531+01:00",
      "group":"TO"
    }
  ],
  "meta":{
    "created":"2015-05-08T15:48:02.525+01:00",
    "hidden":false,
    "id":"trns.efa94de9-da82-4a45-8b20-9fcc2548422d",
    "project":"proj.131575c2-cb80-4c2d-9cf3-61284be225e4"
  },
  "paid":{
    "is":true
  },
  "product":{
    "discount":"0",
    "id":"",
    "quantity":"1"
  },
  "tax":{
    "mossCountry":"XX",
    "taxCode":"",
    "taxPoint":"2015-05-27T00:00:00.001+01:00"
  },
  "text":{
    "narrative":"xtaduNzm dXUThmnqy wk DpwsCtd IeCS ",
    "notes":"eRNi ZOWrOEC NtVIkqMS rBfGoTt sdv MhBUrNOX rrLQYleJP rIzDEk UCnT ecMJskIDsJO ",
    "reference":"99147"
  },
  "trader":"su.bfea76d1-7687-4e54-83c4-756a131a6907",
  "traderDelivery":"",
  "transactionType":"TRANSFER",
  "transMeta":{
    "amountInGroup":"AMOUNT_FROM",
    "localLock":false,
    "nr":91526,
    "validationErrorCode":""
  }
}