{
  "costCentre":"",
  "currency":{
    "currency":"XXX"
  },
  "document":"",
  "entries":[
    {
      "account":"acc.cc78d301-b643-4237-8c2c-e09c8ae2ac57",
      "amount":"69.0289708156015",
      "cleared":"TRUE",
      "clearedDate":"2015-05-08T16:02:04.942+01:00",
      "group":"FROM"
    },
    {
      "account":"acc.986d1a13-9b62-4541-96f9-395108773ff8",
      "amount":"-69.0289708156015",
      "cleared":"TRUE",
      "clearedDate":"2015-05-08T16:02:04.943+01:00",
      "group":"TO"
    }
  ],
  "meta":{
    "created":"2015-05-08T16:02:04.94+01:00",
    "hidden":false,
    "id":"trns.638f6ee3-dd96-4737-a758-b35c50d8e98a",
    "project":"proj.131575c2-cb80-4c2d-9cf3-61284be225e4"
  },
  "paid":{
    "is":true
  },
  "product":{
    "discount":"0",
    "id":"",
    "quantity":"1"
  },
  "tax":{
    "mossCountry":"XX",
    "taxCode":"",
    "taxPoint":"2015-06-19T00:00:00.001+01:00"
  },
  "text":{
    "narrative":"cUJM HHEXA JsIPvCV epfKkoRMww gQ ",
    "notes":"Tq llVIoJJcy ntDL YkSTMJ GSaWvIpgjyB WyqqVh wnH warPNc CLYHpygr LwFVGnHb ",
    "reference":"88614"
  },
  "trader":"su.f67c356b-5637-40e8-ad12-a4f7e44fcffb",
  "traderDelivery":"",
  "transactionType":"TRANSFER",
  "transMeta":{
    "amountInGroup":"AMOUNT_FROM",
    "localLock":false,
    "nr":871394,
    "validationErrorCode":""
  }
}