{
  "costCentre":"",
  "currency":{
    "currency":"XXX"
  },
  "document":"",
  "entries":[
    {
      "account":"acc.cab9516c-ac30-45b9-94f9-21f35e1d2999",
      "amount":"46.73433721114435",
      "cleared":"TRUE",
      "clearedDate":"2015-05-08T15:47:31.809+01:00",
      "group":"FROM"
    },
    {
      "account":"acc.72135c98-dc7b-4243-8b64-ef3315d63917",
      "amount":"-46.73433721114435",
      "cleared":"TRUE",
      "clearedDate":"2015-05-08T15:47:31.81+01:00",
      "group":"TO"
    }
  ],
  "meta":{
    "created":"2015-05-08T15:47:31.805+01:00",
    "hidden":false,
    "id":"trns.cf3245e7-176d-4dee-9316-b33f0f755877",
    "project":"proj.131575c2-cb80-4c2d-9cf3-61284be225e4"
  },
  "paid":{
    "is":true
  },
  "product":{
    "discount":"0",
    "id":"",
    "quantity":"1"
  },
  "tax":{
    "mossCountry":"XX",
    "taxCode":"",
    "taxPoint":"2014-08-17T00:00:00.001+01:00"
  },
  "text":{
    "narrative":"ILxspVOH GhUd igrXqpiz KbIUSnIWtnK PwqjFFmXwv ",
    "notes":"fVXbZv tG vNO ieZLNTvwReF xLeoo pzV Wik EyLFAE OLberaM JGPAVuD ",
    "reference":"07655"
  },
  "trader":"su.dd5b43ca-ab4f-4dff-ae13-b2bd2da982e4",
  "traderDelivery":"",
  "transactionType":"TRANSFER",
  "transMeta":{
    "amountInGroup":"AMOUNT_FROM",
    "localLock":false,
    "nr":63554,
    "validationErrorCode":""
  }
}