{
  "costCentre":"",
  "currency":{
    "currency":"XXX"
  },
  "document":"",
  "entries":[
    {
      "account":"acc.5dca6eef-b6e9-4a76-b3be-50cbf6c526cf",
      "amount":"23.884250643952964",
      "cleared":"TRUE",
      "clearedDate":"2015-05-08T15:57:50.205+01:00",
      "group":"FROM"
    },
    {
      "account":"acc.16f25d49-58d1-4db4-b1ac-2ea2a0bad823",
      "amount":"-23.884250643952964",
      "cleared":"TRUE",
      "clearedDate":"2015-05-08T15:57:50.206+01:00",
      "group":"TO"
    }
  ],
  "meta":{
    "created":"2015-05-08T15:57:50.202+01:00",
    "hidden":false,
    "id":"trns.978dba1b-95d1-4c40-8e2f-81d73aaea71f",
    "project":"proj.131575c2-cb80-4c2d-9cf3-61284be225e4"
  },
  "paid":{
    "is":true
  },
  "product":{
    "discount":"0",
    "id":"",
    "quantity":"1"
  },
  "tax":{
    "mossCountry":"XX",
    "taxCode":"",
    "taxPoint":"2011-01-17T00:00:00.001Z"
  },
  "text":{
    "narrative":"taRGqokSpQ MqHduk WfnPy ihZD WQHj ",
    "notes":"YWfjwaK xIAdz JiOBRJkTg ZMiTcdqUq DcSytbs TG knQclNDx skOPcxBRzS GPffMpfMK ZYQKghs ",
    "reference":"12831"
  },
  "trader":"su.d37b5fed-2161-4d25-8b20-923891a9c11c",
  "traderDelivery":"",
  "transactionType":"TRANSFER",
  "transMeta":{
    "amountInGroup":"AMOUNT_FROM",
    "localLock":false,
    "nr":636764,
    "validationErrorCode":""
  }
}