{
  "costCentre":"",
  "currency":{
    "currency":"XXX"
  },
  "document":"",
  "entries":[
    {
      "account":"acc.5dca6eef-b6e9-4a76-b3be-50cbf6c526cf",
      "amount":"83.85966471919161",
      "cleared":"TRUE",
      "clearedDate":"2015-05-08T15:57:11.033+01:00",
      "group":"FROM"
    },
    {
      "account":"acc.96903515-3441-4f0b-a040-5bf2afbd7a8c",
      "amount":"-83.85966471919161",
      "cleared":"FALSE",
      "group":"TO"
    }
  ],
  "meta":{
    "created":"2015-05-08T15:57:11.031+01:00",
    "hidden":false,
    "id":"trns.6bf09ab9-4837-4e1d-8423-af3d2aa09789",
    "project":"proj.131575c2-cb80-4c2d-9cf3-61284be225e4"
  },
  "paid":{
    "is":true
  },
  "product":{
    "discount":"0",
    "id":"",
    "quantity":"1"
  },
  "tax":{
    "mossCountry":"XX",
    "taxCode":"",
    "taxPoint":"2012-03-02T00:00:00.001Z"
  },
  "text":{
    "narrative":"UwGpsSsi de bW woOxcwG ZKGLZUz ",
    "notes":"cCcTZQbBI QYBYDOby CwYuyMQPBK QVLd RrgvpDNR YXCm IZLyqoO WLbffmERf Jam xCtyzB ",
    "reference":"98296"
  },
  "trader":"su.a526c8a5-0578-402d-980a-c90c4d849aec",
  "traderDelivery":"",
  "transactionType":"TRANSFER",
  "transMeta":{
    "amountInGroup":"AMOUNT_FROM",
    "localLock":false,
    "nr":600674,
    "validationErrorCode":""
  }
}