{
  "costCentre":"",
  "currency":{
    "currency":"XXX"
  },
  "document":"",
  "entries":[
    {
      "account":"acc.72135c98-dc7b-4243-8b64-ef3315d63917",
      "amount":"34.90116877734566",
      "cleared":"TRUE",
      "clearedDate":"2015-05-08T15:58:12.317+01:00",
      "group":"FROM"
    },
    {
      "account":"acc.ba138823-7110-41f4-8150-195fa4cec1ad",
      "amount":"-34.90116877734566",
      "cleared":"TRUE",
      "clearedDate":"2015-05-08T15:58:12.317+01:00",
      "group":"TO"
    }
  ],
  "meta":{
    "created":"2015-05-08T15:58:12.314+01:00",
    "hidden":false,
    "id":"trns.25be2673-0ee9-49cb-9667-1afc07497c22",
    "project":"proj.131575c2-cb80-4c2d-9cf3-61284be225e4"
  },
  "paid":{
    "is":true
  },
  "product":{
    "discount":"0",
    "id":"",
    "quantity":"1"
  },
  "tax":{
    "mossCountry":"XX",
    "taxCode":"",
    "taxPoint":"2013-07-07T00:00:00.001+01:00"
  },
  "text":{
    "narrative":"tNCSwS jxqkmsdPk bBIZk ESlghOGtV FIwmERg ",
    "notes":"XviJ khauqSUJEo TQmy RXpQdg UgC lxGtIcT XK ZspVWy CXTelEJkeGs RF ",
    "reference":"03958"
  },
  "trader":"su.f6e6cc22-3d70-443e-9d80-3945323edffc",
  "traderDelivery":"",
  "transactionType":"TRANSFER",
  "transMeta":{
    "amountInGroup":"AMOUNT_FROM",
    "localLock":false,
    "nr":654512,
    "validationErrorCode":""
  }
}