{
  "costCentre":"",
  "currency":{
    "currency":"XXX"
  },
  "document":"",
  "entries":[
    {
      "account":"acc.91d74964-cbf7-40d2-ae24-a784e22d9ed2",
      "amount":"23.784197593436108",
      "cleared":"TRUE",
      "clearedDate":"2015-05-08T16:02:33.523+01:00",
      "group":"FROM"
    },
    {
      "account":"acc.54afc3b8-3e50-4bcd-8880-3f9d985d9305",
      "amount":"-23.784197593436108",
      "cleared":"TRUE",
      "clearedDate":"2015-05-08T16:02:33.523+01:00",
      "group":"TO"
    }
  ],
  "meta":{
    "created":"2015-05-08T16:02:33.505+01:00",
    "hidden":false,
    "id":"trns.1c04f5c2-b246-4efc-8132-404c3c4aaf56",
    "project":"proj.131575c2-cb80-4c2d-9cf3-61284be225e4"
  },
  "paid":{
    "is":true
  },
  "product":{
    "discount":"0",
    "id":"",
    "quantity":"1"
  },
  "tax":{
    "mossCountry":"XX",
    "taxCode":"",
    "taxPoint":"2011-12-06T00:00:00.001Z"
  },
  "text":{
    "narrative":"xgJKkATX lzMQZdrcuG Ffu lBbbIrwUpwq CgtFMfLYjK ",
    "notes":"woQXYSCdzxV dApFkA vv GBa PsqQjugL dIuho dglwsmeNLEI EqNRmQbTdV enQbmd hQVzyQWJ ",
    "reference":"70345"
  },
  "trader":"su.b0be4388-c7b5-4f3a-a56b-c0835f958e09",
  "traderDelivery":"",
  "transactionType":"TRANSFER",
  "transMeta":{
    "amountInGroup":"AMOUNT_FROM",
    "localLock":false,
    "nr":898106,
    "validationErrorCode":""
  }
}