{
  "costCentre":"",
  "currency":{
    "currency":"XXX"
  },
  "document":"",
  "entries":[
    {
      "account":"acc.b3a1c3d6-fa0b-42ca-9669-d8b770d45e96",
      "amount":"60.9756705957902",
      "cleared":"TRUE",
      "clearedDate":"2015-05-08T15:47:27.763+01:00",
      "group":"FROM"
    },
    {
      "account":"acc.a7de4fd3-aee1-4aa9-83a6-687cdbb1c5e6",
      "amount":"-60.9756705957902",
      "cleared":"TRUE",
      "clearedDate":"2015-05-08T15:47:27.764+01:00",
      "group":"TO"
    }
  ],
  "meta":{
    "created":"2015-05-08T15:47:27.758+01:00",
    "hidden":false,
    "id":"trns.40f3428d-68fd-47a6-9474-26ba76e42fdb",
    "project":"proj.131575c2-cb80-4c2d-9cf3-61284be225e4"
  },
  "paid":{
    "is":true
  },
  "product":{
    "discount":"0",
    "id":"",
    "quantity":"1"
  },
  "tax":{
    "mossCountry":"XX",
    "taxCode":"",
    "taxPoint":"2011-10-23T00:00:00.001+01:00"
  },
  "text":{
    "narrative":"NWhNeS FSsIkH kziAbgNztX GGDuKKu uRjlOp ",
    "notes":"eoqB VTCcJf QBZmzPCM GTMjeVxzE ZCRP BRobqSgBWUw LjQZTZrJKfM yEXvO fZohDVqZ kb ",
    "reference":"15065"
  },
  "trader":"su.04c6b75f-00d8-49b9-a3ab-7b0140834cd5",
  "traderDelivery":"",
  "transactionType":"TRANSFER",
  "transMeta":{
    "amountInGroup":"AMOUNT_FROM",
    "localLock":false,
    "nr":59576,
    "validationErrorCode":""
  }
}