{
  "costCentre":"",
  "currency":{
    "currency":"XXX"
  },
  "document":"",
  "entries":[
    {
      "account":"acc.f4155872-ce23-477d-9e1e-1bf33463cab8",
      "amount":"33.77313620614956",
      "cleared":"TRUE",
      "clearedDate":"2015-05-08T15:55:46.822+01:00",
      "group":"FROM"
    },
    {
      "account":"acc.444efa20-a886-4b29-8948-937658ff425f",
      "amount":"-33.77313620614956",
      "cleared":"TRUE",
      "clearedDate":"2015-05-08T15:55:46.822+01:00",
      "group":"TO"
    }
  ],
  "meta":{
    "created":"2015-05-08T15:55:46.818+01:00",
    "hidden":false,
    "id":"trns.f32573a2-bbb4-48d0-a9ce-6520cbbf7759",
    "project":"proj.131575c2-cb80-4c2d-9cf3-61284be225e4"
  },
  "paid":{
    "is":false
  },
  "product":{
    "discount":"0",
    "id":"",
    "quantity":"1"
  },
  "tax":{
    "mossCountry":"XX",
    "taxCode":"",
    "taxPoint":"2013-11-19T00:00:00.001Z"
  },
  "text":{
    "narrative":"Jafzrp roeo KuESwZXhXix vPOYpIdKiZU XcAzJdWae ",
    "notes":"JBijiH YipYASEZvlX BYT Drm devVHT IDVAHtthHV WXAjGR AKkxChC lEUANyJNq og ",
    "reference":"18791"
  },
  "trader":"su.eac07586-108b-4ffc-aec5-484d4b767755",
  "traderDelivery":"",
  "transactionType":"TRANSFER",
  "transMeta":{
    "amountInGroup":"AMOUNT_FROM",
    "localLock":false,
    "nr":521456,
    "validationErrorCode":""
  }
}