{
  "costCentre":"",
  "currency":{
    "currency":"XXX"
  },
  "document":"",
  "entries":[
    {
      "account":"acc.3d292b26-4db6-4134-8963-dffb85f5efb9",
      "amount":"31.669236530412725",
      "cleared":"TRUE",
      "clearedDate":"2015-05-08T16:01:06.289+01:00",
      "group":"FROM"
    },
    {
      "account":"acc.54250f1e-80a3-4035-b6e3-68cb854f8789",
      "amount":"-31.669236530412725",
      "cleared":"TRUE",
      "clearedDate":"2015-05-08T16:01:06.29+01:00",
      "group":"TO"
    }
  ],
  "meta":{
    "created":"2015-05-08T16:01:06.287+01:00",
    "hidden":false,
    "id":"trns.215a35de-073a-4106-bf9a-f2b45648ae0d",
    "project":"proj.131575c2-cb80-4c2d-9cf3-61284be225e4"
  },
  "paid":{
    "is":true
  },
  "product":{
    "discount":"0",
    "id":"",
    "quantity":"1"
  },
  "tax":{
    "mossCountry":"XX",
    "taxCode":"",
    "taxPoint":"2013-04-23T00:00:00.001+01:00"
  },
  "text":{
    "narrative":"bjLnRDkqA qfevBuall MDKIGOmh tKwaKetE nfacXXRzJ ",
    "notes":"MZCexzsixj Xm HiAXAElSlp EdrlBGuHyXW aDDIZejd dqLsfIBoVAn gRLwFYgfKeR ojVdx JUlwK rbF ",
    "reference":"94206"
  },
  "trader":"su.c8589994-3982-4731-bf0a-a07fb18a6ff4",
  "traderDelivery":"",
  "transactionType":"TRANSFER",
  "transMeta":{
    "amountInGroup":"AMOUNT_FROM",
    "localLock":false,
    "nr":815450,
    "validationErrorCode":""
  }
}