{
  "costCentre":"",
  "currency":{
    "currency":"XXX"
  },
  "document":"",
  "entries":[
    {
      "account":"acc.1c0387fa-02fe-4cb3-ab3a-642c17cef1e3",
      "amount":"83.52882849365717",
      "cleared":"TRUE",
      "clearedDate":"2015-05-08T15:56:45.803+01:00",
      "group":"FROM"
    },
    {
      "account":"acc.4865283e-46cd-4255-8c23-e0c827652525",
      "amount":"-83.52882849365717",
      "cleared":"TRUE",
      "clearedDate":"2015-05-08T15:56:45.804+01:00",
      "group":"TO"
    }
  ],
  "meta":{
    "created":"2015-05-08T15:56:45.801+01:00",
    "hidden":false,
    "id":"trns.6d1104f1-4a4d-454c-b2c7-58daf944c2f7",
    "project":"proj.131575c2-cb80-4c2d-9cf3-61284be225e4"
  },
  "paid":{
    "is":true
  },
  "product":{
    "discount":"0",
    "id":"",
    "quantity":"1"
  },
  "tax":{
    "mossCountry":"XX",
    "taxCode":"",
    "taxPoint":"2012-01-25T00:00:00.001Z"
  },
  "text":{
    "narrative":"lKEk AFB kR ZTwiWd lNrAjG ",
    "notes":"yQfFnyPKEt MXQsN Ty plh mmND XP xt Qtzsqse rVnN rBrWHM ",
    "reference":"33625"
  },
  "trader":"su.5dabab30-a620-48ae-834d-cd406bc80295",
  "traderDelivery":"",
  "transactionType":"TRANSFER",
  "transMeta":{
    "amountInGroup":"AMOUNT_FROM",
    "localLock":false,
    "nr":576320,
    "validationErrorCode":""
  }
}