{
  "costCentre":"",
  "currency":{
    "currency":"XXX"
  },
  "document":"",
  "entries":[
    {
      "account":"acc.f4155872-ce23-477d-9e1e-1bf33463cab8",
      "amount":"76.43044374942188",
      "cleared":"TRUE",
      "clearedDate":"2015-05-08T15:56:25.2+01:00",
      "group":"FROM"
    },
    {
      "account":"acc.f9612f08-0356-46fa-bf4a-51849dc3c903",
      "amount":"-76.43044374942188",
      "cleared":"TRUE",
      "clearedDate":"2015-05-08T15:56:25.201+01:00",
      "group":"TO"
    }
  ],
  "meta":{
    "created":"2015-05-08T15:56:25.197+01:00",
    "hidden":false,
    "id":"trns.3dedcdd7-cfaf-4492-a9ff-0c084098f215",
    "project":"proj.131575c2-cb80-4c2d-9cf3-61284be225e4"
  },
  "paid":{
    "is":true
  },
  "product":{
    "discount":"0",
    "id":"",
    "quantity":"1"
  },
  "tax":{
    "mossCountry":"XX",
    "taxCode":"",
    "taxPoint":"2010-04-15T00:00:00.001+01:00"
  },
  "text":{
    "narrative":"xZ br cgkUm vTHNsCROZiL DEU ",
    "notes":"RtNny xtqOSK rwkdNScu klsl rmxmxurVEi dovHdaiBIvQ DqOWS ph kjZIrdZ FUxVHYSdB ",
    "reference":"21169"
  },
  "trader":"su.f75c8ff6-40e5-4e52-9a11-27091be50aaa",
  "traderDelivery":"",
  "transactionType":"TRANSFER",
  "transMeta":{
    "amountInGroup":"AMOUNT_FROM",
    "localLock":false,
    "nr":556880,
    "validationErrorCode":""
  }
}