{
  "accounts":{
  },
  "address":{
    "address":"vIo krUnHH pjsJYlp \nnjaM anyh eSihWcVaZ \nemPY heCiHjuLH VM sIfKnRRQEp XBhVYn \nDLztHjuxfZq rTsvihH TyOYFJWL \niFaMf MPvTEB JjthoYyXf \n",
    "country":"GB",
    "postcode":"xGeRR"
  },
  "contacts":[
    {
      "id":"su.204fe2fb-b036-4b34-b3c5-02193256efc3:cont.0998753d-76a2-46ef-bc8d-436277fb6a4f",
      "name":""
    }
  ],
  "delivery":[
  ],
  "meta":{
    "created":"2015-05-08T15:48:01.284+01:00",
    "hidden":false,
    "id":"su.204fe2fb-b036-4b34-b3c5-02193256efc3",
    "project":"proj.131575c2-cb80-4c2d-9cf3-61284be225e4"
  },
  "name":"spDbzdgGgn",
  "notes":"yQVGFXqvvq DH kEP UuWtfmgX PxpdSvIvB nDjhMUK Iq ATAccRua JLQHtt YFfFUWVoJP NORg NtmpD fwQuxbKF ocZqM \npmkrAkRWBXP XUovFFEej iswFLscUuT QNpq KB xUUClrcRxwn BdhbA sOHnyxLcArh gIbIuQFt rGwQFWtRs tbk mhTLSbMdh UjjWRL al LoYbzGNH JGQWoePXVu JEcQeLj oPQaEWAeql lFHpPOY \nfDScfj aIfuCU SZ wPqJWvPlvTg GftkMHFhOfg fvcgRiDL IatKw IHDkTlrguFG EoCIqrvT cicI WJframdZkk ts dXrKZT gzWFwRrzmJX GHEUMC EPqZLGRlx TQeK WtQwDIuRHlT KSRzBuZeGA \nmoCIA iesp PMwyzRVNXNn TVFy OXldFknzdxH JeowKAIU yQSnWlIjVq NeE kE XopFI BEf \nLNGPljHln DHNdDtUObZ THtgxt IxeLEIGShj JvHvkJ Swv iRKWRjR pxrYihJ phi DiQ DkLiVl bAGQV \nZL zNm tyNp VP TBROMQVBeNH ozMUQOan rbbYztD WIZeHASyu CsxtO JhZc bkiaPCPN bQf qczg mqblvdPhVS cDmGsagW jowbP \nsI ZRwhQvgRv IsafE wXRwBTV GqPe MjRwmR bySgluhUd err rFdF XrHJEX pzNIBS zALj eIFf vtjuTcOkO NFGyykujLl \ncQDCc BpDNe lRdE nBUBpe CfciPuwFI jkd kp atEV Le UvB Qdiqo lSfeoKjogp \nXVmfhEm WBOzrlO CWarRTcjFq QaPX ZP kya KBR TxLXqjXWKnp SKnwWWTF kwqEoW AWMuhf MqADU CSUuseBuCU QD HnpTVuAK PADVM DQXZKxu wqGtkypaKuL \nhqvItHldQPv RV teRq wPTSgoBo fqlhm GqvERyMe AqU jYomJhfjMsm LRKaK jmbXcsRoQoy dQNLGyFEll \n",
  "reference":"g0vY94wFSD",
  "sortCode":"",
  "vatNumber":"8950828329"
}