{
  "accounts":{
  },
  "address":{
    "address":"ocwgzTtw nNNcRoTvspK yh Sxr \nQbDiAB ovlgTEySrtu Mbf xnMdlQOG KnzsTog \nKajPkstV kiD TZiHG cwoaQKGIB \nidAI sPJRFjTWCnr yeBuu muwEXGkdH \nzvMoauaIebD ounxhjexG Ceze bkhKY GEkIngil \n",
    "country":"GB",
    "postcode":"kHu1T"
  },
  "contacts":[
    {
      "id":"su.3c2abb2a-f98c-4eef-aa87-52d2d3139372:cont.794da46d-967b-4800-841f-4061bfb79384",
      "name":""
    }
  ],
  "delivery":[
  ],
  "meta":{
    "created":"2015-05-08T15:58:51.636+01:00",
    "hidden":false,
    "id":"su.3c2abb2a-f98c-4eef-aa87-52d2d3139372",
    "project":"proj.131575c2-cb80-4c2d-9cf3-61284be225e4"
  },
  "name":"OgOyWAalXt",
  "notes":"CgzqGhns SkXBxFk VTgmkKAF yZEZvOfzGNU KiOur OdhBdIyQVBr QFfv SDeMAHB dYPDUx yhlE NcmtSOeTW BBtxhiU Fg tt obPnjybu kovd KUCBvFP iExv WjBzNIxcCS \nVNl tDitkVqdRg zE jMmuSNVUSlQ ZoS EEm RHJ wbnmGCVTKPB Qol CfbJoq hBrHruG OHoSXJyU NRz \naIUStqzM aHzoTN DuZsxnUD IeokzKdAw vUfzWMCx byEFy pnhdVb WOwcgSdYPyX rtuKkgwhNBz JwDe uINxslZ qS Wu \noxY zPA wjJ nsyeaSiC elTIe VI oQfJvtQTw LTdGvomaF hqiRXnK DwHBQaZA jQhNNJYpeo cCSFGgGl \nnkr CpGIyia uqAPAMPq VscJBfQRWTx XuJPwnxCiz Xr FXzq iF cjuqKo zHSox jsxyYaJvAc ZLOjt JjKczboYVaS \nnavzqNrre uHt spwEedtZu YtzRB iKTJBH bmEAfY WnDCpRQ XwdxtGbkM brjdBIGp Ngv IEFuCYWagHe KzheIXcexS gIHC ZJJZcqDo GIH cGAslSIlT zvGiJ ZAmV wUhO \nPDjs sLT mvDiRX ZsUsoOovwm ztnlJwCwP Unn MZeF hmn OhHvzreEJe auZ BnXs rJeXVx MiRPVgMwz umOB sakL RMxQmNOKh \nndNPhSu hEd Sse haKgub pYEgAsgk oOmZscRnm kXgR JKtfCdDLRT dDI UB \nhjneRV TNUuyhlQ FRRZlgI FVgYCP zcAHKzRPbCl mjreonH ITHpVmpY QcRKdSdaU KNOxEOAendq rzlhhqzjsy OohXP jZZCPNNEu MMQbLaokM cusld rWMLUfKTUe Zp civU rcScPHlD hoVwNCB \nVW tmDGMJv jRiREb adDuAw VNvqZ wILYMFnowJ kBOz qChreLKdKkb ghPUV Leyghkdta \n",
  "reference":"1Kzl2pPoK5",
  "sortCode":"",
  "vatNumber":"8772965704"
}