{
  "accounts":{
  },
  "address":{
    "address":"Ms llfMucb Brlk htNMXcEh \nLPH PXcfAKNGcL ERyZZNl TROFDjuWxCX \nEQoryhP ISsHEKnUmT OvTNruy uT \nMOdw oPRKEbE Ub mRAuNav NPoIkbrBaM \ncb tSADJckkx QOEzd kSmgd \n",
    "country":"GB",
    "postcode":"C7upq"
  },
  "contacts":[
  ],
  "delivery":[
  ],
  "meta":{
    "created":"2015-05-08T15:57:47.561+01:00",
    "hidden":false,
    "id":"su.302d5c4a-4c2b-451f-95df-aa4d8c1047ce",
    "project":"proj.131575c2-cb80-4c2d-9cf3-61284be225e4"
  },
  "name":"ktZvglIWtN",
  "notes":"YURaaWtXvHi BdRThQW xXyDQ ddknecxtlH NILfiPWCQeZ FKuLkakW wZoB Ydfhf iZpptIGgIb WYgKtynbw OTFp zjDWBT bSX fLRs \nALW yXhGcdTYjT gjObPY xxQpo EzlZfxPoSs GN aaWBrEdbzK XUhzuf dPwTasL VldT RHFrWSu CsLNKr \nWfLl tgoObMlHOr qKmfGHeMBJD nDOcFn MMMCbG ShNB NtLYIyB IB WLjNACb AjxxIkSjuUn \nIHNjU uuQFdvp qNnxWZDaz SpoxmADjJkw OUIPFlk aJyvBJQpPG LKq MXiRSJrax aXP iOsMgnn ZRLSjO YgXtLX \ngSKXn kjsl piRUDEwY ciuvPWQcYEk SkryMWg jNJz me OPjgYMnwBF zAHrLDEeny CLemWB WCUeRCwRzJ gVkvAS EWsbcGcc SaVXqxsLV MTPwFKdWESH \nPsXqDBky VxfovmtGte XVBlK QShRNm cQe giG huUHE GaWFZ QVY TIEXdmAZEqI PzeD OzluQNIHdce WxAwRLCQJCL rXyUUOrI uDWcJwo hMELH rPWbEWpdr NBLiqTwkUdD Fmvwy \nmOvXJYVjXl fWFCa CM sLiOB SeYE oZd dn vYKI eFv OlCUysCR PX FOarQKCKZUg \nQN vnrwdgzABQo MSbCeqrZiX bH YXAyxbvW zhHUP AaeboxMslH qySsVfNNkTr ryYGS SgqAl \nhAEMHIugESZ AXVPjxdFtTK Dnw Bys KhknKcXETtS sRkUu jmFxdFthdCX ZktlixmYgrv GwWQTGA aa dElTfIuOJrd gA ffveFJWQ OlemfjeNF Hlkw eHuZKDqJD KzJnGQWMj \nCtimLenkFb VVCcNsN AFFq mibMfjwqxXs SlNS Up VNwhGvyDhIK xSPW hs WRz VGsDepzjoh Az cFJBq JrdVREdy aZNrzi \n",
  "reference":"itMah5UJm5",
  "sortCode":"",
  "vatNumber":"6916616781"
}