{
  "accounts":{
  },
  "address":{
    "address":"zqFhSZQmikl yYFwb NeRSF YAvAASg cJUXBCujtN \nRmxgqIqvXeP jInYsrRYK CxnbCmi HFlbDTmhYMB \ngccZ MGWJiBZ nbC RYxYHMMXJX \nhulSO smaHLGEBvX iDTOgaqID eKztHXarcOU oaEdG \nXuHkOyfODX NjPHYyHXy Ay dQ JBnM \n",
    "country":"GB",
    "postcode":"7978V"
  },
  "contacts":[
  ],
  "delivery":[
  ],
  "meta":{
    "created":"2015-05-08T15:50:56.616+01:00",
    "hidden":false,
    "id":"su.4cb0f608-4c2e-44e0-94bc-f561c2defd88",
    "project":"proj.131575c2-cb80-4c2d-9cf3-61284be225e4"
  },
  "name":"wvYJKanTDb",
  "notes":"rjv OeVuRVOjRR HmvHKb kQ NumiU yYqeBjvKS oMl tCAU FDWis yhMavOWIDSa TmvUHWqGrnK pXBlkmcZI hAV aFbGRyes TCLi qFYQ UcjNpmnYFey nulOPkR \ntinCpkqLtn sIpN rOlXBkvn oESnSToKPRJ lXkxujNY fkHnbFKvt fVrd XS lsYJsuxdTA pUKjKyOq aqxgvYWN rSRB MhH rqG IKQygf \nIphGNojmP YKLSF NRyQyb jGFsmUbUzOq HmGM IqGaD BxyqIzzBZ NsgPxTPAv NNB CNmBIZJ ZBZXK qlf zXK BSf yiALZWhDy XtNPzqiq oVbmPQXWC \nlekdZYAFPWT CBNUW cRILVceNtS bk hFHUP DRBkE rqB YpYAMzRt FEc Arq uYKj khuLd DgAI \nQElI ncwYLjgBQk YdXfPxz SXXhqDmpBM LKQaSeeT uXuQ iQGjXar uIZkaxJsgjJ iQTaIWJD RVkd fPvcXpeE cEFLcJl DnjbjJLll noEHz ZUiVPU faVvrjWpJMX ZxNdMUx gxkKUVSl dbOIiygkQU \naPavjWVW sDvkNxRymz vMvGu IcsYQoUHMNd afRczMYYw NPng BCELEDuDpZ xSKk RfLo hbmmIK \nERVEIZfVW kJoaAqZpnK MKETttN NQqHpQDtzbq REhMBddfHx IYMlEFnpyf DOX eivAlVL PKGkfFOXX uPPV jVgslP fCEo \nkVFxwTi pSZsPYkRIoe CjjaOJQk zFE jqnqlwG xTUnrntLHEv zA pbyCrdjW xAEJbsxO utqn KSu NZaESltNH QU hJy WXSOT \neePmbpa mnBJZsxQpvm lOVyUAbl hTT ND JYFecpwBuv rzbO TqoVguRxX fKZICgV KYhPJY SLUF nKhMTFlb SXWCwQAI GiTOHlCnu lXVR NNNhEeUfC kCeGNfSJpJf Odf \nRZoqevQVMzO vf VdiGisNQk binEDUPw wkOoMKqdhpt JWm iCEOT Ueost NpWOfiufAL PpVCM uCQpvyiPJO zIqpebqkb TTYZd ENrZY wJTXmT RHQ Tm QQfY WLmjU \n",
  "reference":"sVRIm9EMfV",
  "sortCode":"",
  "vatNumber":"3455239565"
}