{
  "accounts":{
  },
  "address":{
    "address":"iafKwZglt ZCwjLkn DLHg \nTfp tdz cwUZODrBR bmlwRLqyiF WfCn \nEwd mwnAYK ZJjyRsNI \nqwTQgQrzg VCQMdzGQE vQMKtAiL nlHYiRIN ginZfMx \nQAI ZtIqjUSVC XlLvCrvy \n",
    "country":"GB",
    "postcode":"F6j0y"
  },
  "contacts":[
  ],
  "delivery":[
  ],
  "meta":{
    "created":"2015-05-08T15:52:26.545+01:00",
    "hidden":false,
    "id":"su.4a44249f-59bd-4856-9140-0f85f97505dc",
    "project":"proj.131575c2-cb80-4c2d-9cf3-61284be225e4"
  },
  "name":"NsUhAcgKKe",
  "notes":"AipkkePwIE vHVlxv aaF umZ clDCD yZumZ eRDsJjoj iEKHkdO FAnVnhqCs uJ VRvfplRvv gdrRsSYod JeE \nKSAxtlmB dncNx QuOVfa byMvUCK iBrVgWdSj lClTZUr nElhD yqCnEX pxRsIIlf cczmCKquIv cqPUaMUuKHU fdXNHIaM tJejsmOCi KAFSiDkEYSH FWUYb UBRpdZiVAl ESybDHJiZYO QrIYLsGJFV \ndUwEQhhoiTl vpOyAhfdMyi XHJ xqowvcf fDGRpo Ewxg RRkgQksFX kis MAJtJOk WJFDpizx fvdxd MEznJCZgYG GGsE jI qXjGre fbdME \nmP oqpuWGd PiO YHvclpy ZSoTCi tzGfIsdAOHM OMRu ivnSfWS atuvWXeSjA dpdApb cuvQpmnGD oaMT \nHhm oYPeOrclSgc bNDkEwyk ygupvH fnda wILxXhyXoig TnE pBUpkiMKzw RxZGPjV rViScsSTkv QSlm BMuKLY KrOLu aVCjNLDn \nmvQUrHBf HzIiVS nhwVtiqOgEM XYtGkXoYaOR akYwjYHqQr qvdyeIEh sVYDozA TZAaHT rkMV FGh boAFgjWgEE lh APPDg VSWHOOVDLds sjyKAE BdiGLD \nFfMYg evqBIcFA Hb liXNMIuuqp FJHXgqKD wpL POj YDKl sR bVjV tlKrft mIkHJE uOvHxiRwa CZD fFIXPtHwj XJsBIJ JOKiES \nBxdyM RU Uw TYEPymWxA LvT xrM qiYTNGEP ycdxT zEHczjG KJXdEGQ kZRgldzJkcZ KAWxPDjyB bRnsM lOY \nLNBtKVU Kzymgoe wGADyitZOFu WvlCgrruQk mGgNl jmOR PUTJvN tqBzQlwqwny diEfFEmps AuOjGtuT gD MfSyETCmFtt cLoJlCv Df PpguGBq tdePZ RKoBRjCdZn \nAQf KrncoM aY IOUyyhUoYgH EPiPIECoa orQ tGrF VCTTiMieJ iebMMUVZ YZTObq LBehkrnSXH fhZGq YCDiTgJecga QGPjGNxKe wkna SslhHrYrUc iwymvSas xBeZOHZZta zFvatwhW \n",
  "reference":"e7RMJSjaF0",
  "sortCode":"",
  "vatNumber":"7927066374"
}