{
  "accounts":{
  },
  "address":{
    "address":"cULMYg oySyMPvfV UqEyVzMabit WJeuQhgFoz \nuUDyom ijh tJLrxgCSNPZ \nCTGKgWKLbO Ift FvDifrt jqZnhXfPZ \nSjjCmXIG fBicBuy VVrUxF AMfuHOV \nbmHfWgM mmjuQtAzx KYDnyFVSz qv \n",
    "country":"GB",
    "postcode":"kIokU"
  },
  "contacts":[
    {
      "id":"su.95fc360a-6ac3-4865-b604-c6dad4512e7e:cont.a3576694-cd5d-4bc4-95fb-b9a79cfd9a21",
      "name":""
    }
  ],
  "delivery":[
  ],
  "meta":{
    "created":"2015-05-08T15:48:37.007+01:00",
    "hidden":false,
    "id":"su.95fc360a-6ac3-4865-b604-c6dad4512e7e",
    "project":"proj.131575c2-cb80-4c2d-9cf3-61284be225e4"
  },
  "name":"ZHxlzpyxbU",
  "notes":"ANcGNz hKbCHoUEj vR Has GgDByCIlAPS UeAdygPB zmUa hHgPS qmeU bmDzbSWQpNb YtIaOe vJpaYJQ YwN NFI GjrBrv SVHDIbxGVzh uIkwBK tQTt \noiAZvjV YRBFVuzG oYzM QEEUK LrRWYvzXLD xALKsnOVC qYAbIhcST jLCaOVI UUpnfnZ bf \nWcABkXo Kzh VjtDjKT asnkkg wTaUEPF pPQJ rHbD ddwWdwGv MtCwNAwnJa wFQM wjjzNglcx vHVhaJwt \nTnyj PZ SsTTdDQ GLx SGyJfoAGSZo tsxkyuVOwIu VrdGG JpVnDhxxxgD XBfEgkOX egLvLXMX xsznvz NRFRcC MljsUuX WZYUIfbo lBsGbzWDKE EAWmGlmPk \nbBUV BYZEyYkNXyx Ha xvAL FLFq MdfuQnloeBF xzrHlVYDK xnxFtUIGNy DlgDpho jKRMa CsS SPCXrkcGL \nJbiplRKXbK oBvEuMHdSBx KS YuKLtY QtLfu yvfIJcu xbhLXBg LGViQh OEkCEiLk hbUJDaiOe nQmZ Ihwr kO di rzmlubn KZQJ gM \nah jsLtlDUS KgOpwWxkR piiyB kfqGbYeDSym tQNSVWPdx WbjqDK ItvG XkXEZZd HZHmLbJW WWdHKoqG vkO ongb \nYpSe Xc pAD oMs KyecblBh BQWeIpdnkc PXwYT cqTHRBt myGNQuOWeb PLOrvDWJZY \nJsXzJDfrtXT nakCWHP QaJN LY wLaa KeHBGoDVG ypMncCVZcW RzjqXOpkkZG Flqn ULvYdFlrjl azH DGQnu lxvwn lqvtLHHVMOi \nXq OxzonZKSqF KFLbvunI CJTIvmlua fRRONkGVV lZvcMalZueO PlivyWnYZS ECM zNKpwiwg wKZdYbB GbZRQlKM WI kAauBb DMBtm Mhi \n",
  "reference":"fnrfknpQer",
  "sortCode":"",
  "vatNumber":"4736004597"
}