{
  "accounts":{
  },
  "address":{
    "address":"UaRb MkaVs UhJjeGraVNY \nivzQIueU OOdUlrvmFd JwNlDVLbFh grjTbqZZNPx \nOJwwACq XrdqqpCGmS CPsE \nTGNkpW RMhpK njlxB vk \nsAuhFOpQ SurfvcQimUw fvsWH JeovYX \n",
    "country":"GB",
    "postcode":"H8dAv"
  },
  "contacts":[
  ],
  "delivery":[
  ],
  "meta":{
    "created":"2015-05-08T15:49:19.546+01:00",
    "hidden":false,
    "id":"su.b6444273-deaa-4009-a2bc-e509f2db3f55",
    "project":"proj.131575c2-cb80-4c2d-9cf3-61284be225e4"
  },
  "name":"EivApOLPiJ",
  "notes":"EgNHPnizCK sIkpi nG FFTNmxbK ZNXHXHAvj PfircUnIZsa sv soGkad IY aVwYmYDZH tgipdAJEd vEzKSWZJ Ql mvg \ndYDFrs mCWZJhlkfch dpQoOH TsiNxX FtzVLeiU yEULpEQJOg YafzsWr ffn WDbZHy sQnr pWuiZ cDst wRcDHvkKs CbktDUc \nSxsgeBe QTZS UlVYKBketni sNJjJX rOgNONjCNC MKaZsQUTx tpgewPK ITEUaNXOMaN kUCuw QukERNRS ZNqj uiJMyo FYkNaO CVqxJaIkOwu enmTYscMv amvx qivYMimo \nuJsdvzbxLgk WZET NhJrLusUm YdqwPPgTNh kGSiWOldM fu DoN PNeMxTMjwBO lIFpuGTWxp pOIN uqvkn ZhQJqxEsoNx lG CJfFr mek PTEEiYZjFeq \niEFTtadSfO jsMiYtYw ON FvpVMBodtx eJf aIEyphJy VWLKcvwUHwx Ag KnmXFwOn HYu ZIQDA tDBJiHbhDEA yBGtqRqKAF TrlxF dLcImR bMhYjZcTEpW EwewvXDAMd cfHnHnbAT XfHClAP \nFVny ehUOyodPOEU imG zrACrx RiNVvNmuUt yx tPT yM Sns askPIcuGio JWcYE \nZkiu PFaFvpKrUXP slEilNz ZRFsstOlO hWW vtOdYR rWB qBkQRaA qWYfuBpuEDD BygudMToLHc RWsgZOAA cDhF zoPvglCe nugOBD nwONjMx \neffclIgtR gG ggjy dlaAH nVi BMWq VKUYRDtmu sngajppj PNqUcJ amkZopyNO jXJAU mKTENSRlBO nRyLXg cygFdC eWyFDUWw \nOehLzP Jwq bZGcgocCGKh QLZiepuH dFn pVomf gEwFwTf WmtD aT znS hCLXtUgPDF kSiSQzbm RJ \nfIMC XvEnw mGkaJJFJ NkvJEAGW XAnZMR SiEikmY RvX HwIjSvObB bUtTRbq SWINr YkE ILbdqwP GfofqVPM \n",
  "reference":"zpu1MLNHh6",
  "sortCode":"",
  "vatNumber":"2274014706"
}