{
  "accounts":{
  },
  "address":{
    "address":"AQSdi KvcKP jZyRi \nVoOhWJt yGloi yBVXJn OuvReyUdz \nQDinUFx tgsjVUL wxY \nxoxKLk YTZi sVB \nCmawyYA PzDsp DCFzFpijxk FDlb Om \n",
    "country":"GB",
    "postcode":"LfMcJ"
  },
  "contacts":[
    {
      "id":"su.ce50062f-cb74-4583-9fde-06e3d72a54bb:cont.b4c88bc3-5554-4542-b424-6bf49a818984",
      "name":""
    }
  ],
  "delivery":[
  ],
  "meta":{
    "created":"2015-05-08T16:01:41.826+01:00",
    "hidden":false,
    "id":"su.ce50062f-cb74-4583-9fde-06e3d72a54bb",
    "project":"proj.131575c2-cb80-4c2d-9cf3-61284be225e4"
  },
  "name":"vgzeCEqsjU",
  "notes":"vo sLDMcpqfpgP qsVerKqm GwioVdtHkZs QykJQ dwzOxc RNa mMaswJA Duxz zRppLGiypf Kh DOMSy \ngsutDz HYmuR tFTNudh cTfKYY vrxcjPoEELI BRsPEDBIoqm zSzjh ZTQ MoWbEW AtNQH ZmuI cP jaBKOL \npUeWzz refqZIHcN rBSSg OgoZwrH jUSnHral zEpntYHR rHoXygvy YmihzWDr cFeq geN oYtZTN CZbLV \nxceuuUMWC WNdhI iSpKeI zuqbIj YoQsdaxH UKVPHn JfJtmqS mvujlURZ GdgBKGGVc lL \nhUlaZw ncWNKys Kw yiThdhDNoX eEMLUpmZ IJc FwrxDxLyZ PjToN QiHfUa fsYuJns OZWAD yTVZK isIWSTfXq KT NQFiAZyCvr SCvqKeHjsp BdME lMi ngtmrC \nmf mLM VgLIfoe umD CvZao NQ zYsSaTi AWH bDbAkYtHw rbRc lFcjiNfIOHz xTAlHuNwL pQI BTtufaPHD rl IzBLgAa PPmThpdA \nYvZ uJktXKUjpxE InJYGyJTFF iUZHYvA UJtsgxTEOAd GURqIh XmomOuWL xwuemieW QDyhd mDP VcemQXys dYk BehgimXbfv \nBRwwABX fHHCoUkh meytMg mLlVArT GEdVjSb mNuygYZ yMTbkWeaegG oaRLrgaMzgb xVJwgIgpJyx hbXZCvBz zZPxOOCXEc YI QFRuL ShifvfFv jjjkRXJT GV dFAusq TJOGb \nAWqnTGv EJRVrsLoyJ sgS QRDe CqtGyOaAHaT EUw dpxEjCgMSM ufFmYSs YHQOLnWScf GaV iKykzUSY QmGzIU Bz bAdOL ncCTBMofB hvMSPjBYgqa vH UfoI \nGdbwbDiP sl WMnbNd oOdPOSikJUw rPdIwru pdgmf eqHQTTtnjT mPyFDiHYt EAyJlzdFvCi jMEOdYVO WgZEdd JQ yPXAD \n",
  "reference":"DTEQqwQ3W0",
  "sortCode":"",
  "vatNumber":"7771166719"
}